gradient_figlet/__init__.py
gradient_figlet/__main__.py
gradient_figlet/pleasing_items.py
gradient_figlet-0.5.0.dist-info/LICENSE
gradient_figlet-0.5.0.dist-info/METADATA
gradient_figlet-0.5.0.dist-info/WHEEL
gradient_figlet-0.5.0.dist-info/top_level.txt
gradient_figlet-0.5.0.dist-info/zip-safe
gradient_figlet-0.5.0.dist-info/RECORD
