Metadata-Version: 2.1
Name: gradient-figlet
Version: 0.5.0
Summary: Prints beautiful gradient figlets to the terminal
Home-page: https://github.com/wasi-master/gradient_figlet/
Author: Wasi Master
Author-email: arianmollik323@gmail.com
License: MIT
Project-URL: Documentation, https://github.com/wasi-master/gradient_figlet#readme
Project-URL: Source, https://github.com/wasi-master/gradient_figlet
Project-URL: Changelog, https://github.com/wasi-master/gradient_figlet/blob/main/CHANGELOG.md
Platform: any
Classifier: Development Status :: 4 - Beta
Classifier: Programming Language :: Python
License-File: LICENSE
Requires-Dist: colour
Requires-Dist: rich
Requires-Dist: click
Requires-Dist: rich-click
Provides-Extra: testing
Requires-Dist: setuptools ; extra == 'testing'
Requires-Dist: pytest ; extra == 'testing'
Requires-Dist: pytest-cov ; extra == 'testing'
